.coveragerc
.pylintrc
CHANGES.rst
MANIFEST.in
README.rst
setup.cfg
setup.py
tox.ini
sphinxdocs/CHANGES.rst
sphinxdocs/README.rst
sphinxdocs/conf.py
sphinxdocs/index.rst
sphinxdocs/threadverify.rst
src/crl/__init__.py
src/crl.threadverify.egg-info/PKG-INFO
src/crl.threadverify.egg-info/SOURCES.txt
src/crl.threadverify.egg-info/dependency_links.txt
src/crl.threadverify.egg-info/namespace_packages.txt
src/crl.threadverify.egg-info/requires.txt
src/crl.threadverify.egg-info/top_level.txt
src/crl/threadverify/__init__.py
src/crl/threadverify/_version.py
src/crl/threadverify/dumptrace.py
src/crl/threadverify/threadingmonkeypatch.py
src/crl/threadverify/threadlistener.py
src/crl/threadverify/threadstatics.py
src/crl/threadverify/threadverify.py
tests/__init__.py
tests/test_threadverify.py
tests/robottests/CreateThread.py
tests/robottests/__init__.py
tests/robottests/createinloop.robot
tests/robottests/createinloopleaveone.robot
tests/robottests/newthreads.robot
tests/robottests/newthreadsleavelast.robot
tests/robottests/nothreads.robot