Metadata-Version: 1.1
Name: crl.threadverify
Version: 1.0
Summary: Robot Framework thread management verification library
Home-page: https://github.com/nokia/crl-threadverify
Author: Petri Huovinen
Author-email: petri.huovinen@nokia.com
License: BSD-3-Clause
Keywords: robotframework thread
Platform: UNKNOWN
Classifier: Intended Audience :: Developers
Classifier: License :: OSI Approved :: BSD License
Classifier: Programming Language :: Python :: 2
Classifier: Programming Language :: Python :: 2.7
Classifier: Programming Language :: Python :: 3
Classifier: Programming Language :: Python :: 3.6
Classifier: Programming Language :: Python :: 3.7
Classifier: Topic :: Software Development
